{
    "view":[

    {"date":"01-11-2022","view": 100},
    {"date":"02-11-2022","view": 250},
    {"date":"03-11-2022","view":300},
    {"date":"04-11-2022","view": 280},
    {"date":"05-11-2022","view": 400},
    {"date":"06-11-2022","view": 520},
    {"date":"07-11-2022","view":500},
    {"date":"08-11-2022","view":640},
    {"date":"09-11-2022","view":700},
    {"date":"10-11-2022","view": 660},
    {"date":"11-11-2022","view": 700},
    {"date":"12-11-2022","view": 720},
    {"date":"13-11-2022","view":750},
    {"date":"14-11-2022","view": 770},
    {"date":"15-11-2022","view": 780},
    {"date":"16-11-2022","view": 750},
    {"date":"17-11-2022","view":800},
    {"date":"18-11-2022","view":1000},
    {"date":"19-11-2022","view":700},
    {"date":"20-11-2022","view":900},
    {"date":"01-11-2022","view": 100},
    {"date":"02-11-2022","view": 250},
    {"date":"03-11-2022","view":300},
    {"date":"04-11-2022","view": 280},
    {"date":"05-11-2022","view": 400},
    {"date":"06-11-2022","view": 520},
    {"date":"07-11-2022","view":500},
    {"date":"08-11-2022","view":640},
    {"date":"09-11-2022","view":700},
    {"date":"10-11-2022","view": 660},
    {"date":"11-11-2022","view": 700},
    {"date":"12-11-2022","view": 720},
    {"date":"13-11-2022","view":750},
    {"date":"14-11-2022","view": 770},
    {"date":"15-11-2022","view": 780},
    {"date":"16-11-2022","view": 750},
    {"date":"17-11-2022","view":800},
    {"date":"18-11-2022","view":1000},
    {"date":"19-11-2022","view":700},
    {"date":"20-11-2022","view":900}
]
}